ga4_mcp_server.py
mseep_google_analytics_mcp-1.2.2.dist-info/METADATA
mseep_google_analytics_mcp-1.2.2.dist-info/WHEEL
mseep_google_analytics_mcp-1.2.2.dist-info/entry_points.txt
mseep_google_analytics_mcp-1.2.2.dist-info/top_level.txt
mseep_google_analytics_mcp-1.2.2.dist-info/RECORD
